comm/__init__.py
comm/comm.py
comm/comm_files.py
comm/comm_json.py
comm/comm_log.py
comm/comm_path.py
comm/comm_re.py
comm/comm_root.py
comm/comm_scrape.py
comm/comm_sleep.py
comm/comm_telegram.py
comm/comm_time.py
comm/comm_updating_printer.py
comm/sqlite_manager.py
commmj-0.1.0.dist-info/METADATA
commmj-0.1.0.dist-info/WHEEL
commmj-0.1.0.dist-info/top_level.txt
commmj-0.1.0.dist-info/RECORD
