Metadata-Version: 2.1
Name: commmj
Version: 0.1.0
Summary: Common code snippets
Home-page: UNKNOWN
Author: marin-jovanovic
License: MIT
Platform: UNKNOWN
